digitalhub/__init__.py
digitalhub/context/api.py
digitalhub/context/builder.py
digitalhub/context/context.py
digitalhub/entities/__init__.py
digitalhub/entities/builders.py
digitalhub/entities/_base/__init__.py
digitalhub/entities/_base/_base/__init__.py
digitalhub/entities/_base/_base/entity.py
digitalhub/entities/_base/context/__init__.py
digitalhub/entities/_base/context/entity.py
digitalhub/entities/_base/entity/__init__.py
digitalhub/entities/_base/entity/builder.py
digitalhub/entities/_base/entity/entity.py
digitalhub/entities/_base/entity/metadata.py
digitalhub/entities/_base/entity/spec.py
digitalhub/entities/_base/entity/status.py
digitalhub/entities/_base/executable/__init__.py
digitalhub/entities/_base/executable/entity.py
digitalhub/entities/_base/material/__init__.py
digitalhub/entities/_base/material/entity.py
digitalhub/entities/_base/material/spec.py
digitalhub/entities/_base/material/status.py
digitalhub/entities/_base/material/utils.py
digitalhub/entities/_base/runtime_entity/__init__.py
digitalhub/entities/_base/runtime_entity/builder.py
digitalhub/entities/_base/unversioned/__init__.py
digitalhub/entities/_base/unversioned/builder.py
digitalhub/entities/_base/unversioned/entity.py
digitalhub/entities/_base/versioned/__init__.py
digitalhub/entities/_base/versioned/builder.py
digitalhub/entities/_base/versioned/entity.py
digitalhub/entities/_commons/__init__.py
digitalhub/entities/_commons/enums.py
digitalhub/entities/_commons/metrics.py
digitalhub/entities/_commons/utils.py
digitalhub/entities/_constructors/__init__.py
digitalhub/entities/_constructors/_resources.py
digitalhub/entities/_constructors/metadata.py
digitalhub/entities/_constructors/name.py
digitalhub/entities/_constructors/spec.py
digitalhub/entities/_constructors/status.py
digitalhub/entities/_constructors/uuid.py
digitalhub/entities/_processors/__init__.py
digitalhub/entities/_processors/processors.py
digitalhub/entities/_processors/utils.py
digitalhub-0.14.9.dist-info/METADATA
digitalhub-0.14.9.dist-info/WHEEL
digitalhub-0.14.9.dist-info/licenses/AUTHORS
digitalhub-0.14.9.dist-info/licenses/LICENSE
digitalhub-0.14.9.dist-info/RECORD
