Metadata-Version: 2.4
Name: digitalhub
Version: 0.14.9
Summary: Python SDK for Digitalhub
Project-URL: Homepage, https://github.com/scc-digitalhub/digitalhub-sdk
Author-email: Fondazione Bruno Kessler <digitalhub@fbk.eu>, Matteo Martini <mmartini@fbk.eu>
License:                                  Apache License
License-File: AUTHORS
License-File: LICENSE
Keywords: data,dataops,kubernetes
Classifier: License :: OSI Approved :: Apache Software License
Classifier: Programming Language :: Python :: 3.9
Classifier: Programming Language :: Python :: 3.10
Classifier: Programming Language :: Python :: 3.11
Classifier: Programming Language :: Python :: 3.12
Requires-Python: <3.13,>=3.9
Requires-Dist: boto3
Requires-Dist: gitpython>=3
Requires-Dist: numpy
Requires-Dist: psycopg2-binary
Requires-Dist: pyarrow
Requires-Dist: pydantic
Requires-Dist: python-slugify
Requires-Dist: pyyaml
Requires-Dist: requests
Requires-Dist: sqlalchemy
Provides-Extra: dev
Requires-Dist: bumpver; extra == 'dev'
Requires-Dist: jsonschema; extra == 'dev'
Requires-Dist: pytest; extra == 'dev'
Requires-Dist: pytest-cov; extra == 'dev'
Provides-Extra: full
Requires-Dist: mlflow==2.19; extra == 'full'
Requires-Dist: pandas; extra == 'full'
Provides-Extra: mlflow
Requires-Dist: mlflow==2.19; extra == 'mlflow'
Provides-Extra: pandas
Requires-Dist: pandas; extra == 'pandas'
